ib_async/__init__.py
ib_async/client.py
ib_async/connection.py
ib_async/contract.py
ib_async/decoder.py
ib_async/flexreport.py
ib_async/ib.py
ib_async/ibcontroller.py
ib_async/objects.py
ib_async/order.py
ib_async/py.typed
ib_async/ticker.py
ib_async/util.py
ib_async/version.py
ib_async/wrapper.py
ib_async-1.0.2.dist-info/LICENSE
ib_async-1.0.2.dist-info/METADATA
ib_async-1.0.2.dist-info/WHEEL
ib_async-1.0.2.dist-info/RECORD
