Metadata-Version: 2.1
Name: ib_async
Version: 1.0.2
Summary: Python sync/async framework for Interactive Brokers API
Home-page: https://github.com/ib-api-reloaded/ib_async
License: BSD
Keywords: ibapi,tws,asyncio,jupyter,interactive,brokers,async,ib_async,ib_insync
Author: Ewald de Wit
Maintainer: Matt Stancliff
Maintainer-email: matt@matt.sh
Requires-Python: >=3.10
Classifier: Development Status :: 4 - Beta
Classifier: Intended Audience :: Developers
Classifier: License :: OSI Approved :: BSD License
Classifier: License :: Other/Proprietary License
Classifier: Programming Language :: Python :: 3
Classifier: Programming Language :: Python :: 3.10
Classifier: Programming Language :: Python :: 3.11
Classifier: Programming Language :: Python :: 3.12
Classifier: Programming Language :: Python :: 3 :: Only
Classifier: Topic :: Office/Business :: Financial :: Investment
Requires-Dist: eventkit
Requires-Dist: nest_asyncio
Project-URL: Bug Tracker, https://github.com/ib-api-reloaded/ib_async/issues
Project-URL: Repository, https://github.com/ib-api-reloaded/ib_async
